<?xml version="1.0" encoding="utf-8"?>
<!DOCTYPE hibernate-mapping PUBLIC "-//Hibernate/Hibernate Mapping DTD 3.0//EN"
"http://www.hibernate.org/dtd/hibernate-mapping-3.0.dtd">
<!-- 
    Mapping file autogenerated by MyEclipse Persistence Tools
-->
<hibernate-mapping>
    <class name="org.ike.youme.entity.Browse" table="browse" catalog="youme">
        <id name="browseId" type="java.lang.Integer">
            <column name="browseId" />
            <generator class="native" />
        </id>
        <many-to-one name="activity" class="org.ike.youme.entity.Activity" fetch="select">
            <column name="activityId" />
        </many-to-one>
        <many-to-one name="user" class="org.ike.youme.entity.User" fetch="select">
            <column name="userId" />
        </many-to-one>
    </class>
</hibernate-mapping>
