<?xml version="1.0" encoding="utf-8"?>
<!DOCTYPE hibernate-mapping PUBLIC "-//Hibernate/Hibernate Mapping DTD 3.0//EN"
"http://www.hibernate.org/dtd/hibernate-mapping-3.0.dtd">
<!-- 
    Mapping file autogenerated by MyEclipse Persistence Tools
-->
<hibernate-mapping>
    <class name="org.ike.youme.entity.User" table="user" catalog="youme">
        <id name="userId" type="java.lang.Integer">
            <column name="userId" />
            <generator class="native" />
        </id>
        <property name="account" type="java.lang.String">
            <column name="account" length="15" />
        </property>
        <property name="pwd" type="java.lang.String">
            <column name="pwd" length="32" />
        </property>
        <property name="nickname" type="java.lang.String">
            <column name="nickname" length="15" />
        </property>
        <property name="head" type="java.lang.String">
            <column name="head" length="100" />
        </property>
        <property name="age" type="java.lang.Integer">
            <column name="age" />
        </property>
        <property name="sex" type="java.lang.String">
            <column name="sex" length="2" />
        </property>
        <property name="name" type="java.lang.String">
            <column name="name" length="20" />
        </property>
        <property name="sign" type="java.lang.String">
            <column name="sign" length="30" />
        </property>
        <property name="city" type="java.lang.String">
            <column name="city" length="50" />
        </property>
        <property name="createTime" type="java.sql.Timestamp">
            <column name="createTime" length="19" />
        </property>
        <set name="comments" inverse="true">
            <key>
                <column name="userId" />
            </key>
            <one-to-many class="org.ike.youme.entity.Comment" />
        </set>
        <set name="activities" inverse="true">
            <key>
                <column name="userId" />
            </key>
            <one-to-many class="org.ike.youme.entity.Activity" />
        </set>
        <set name="browses" inverse="true">
            <key>
                <column name="userId" />
            </key>
            <one-to-many class="org.ike.youme.entity.Browse" />
        </set>
        <set name="collects" inverse="true">
            <key>
                <column name="userId" />
            </key>
            <one-to-many class="org.ike.youme.entity.Collect" />
        </set>
        <set name="footprints" inverse="true">
            <key>
                <column name="userId" />
            </key>
            <one-to-many class="org.ike.youme.entity.Footprint" />
        </set>
        <set name="attends" inverse="true">
            <key>
                <column name="userId" />
            </key>
            <one-to-many class="org.ike.youme.entity.Attend" />
        </set>
    </class>
</hibernate-mapping>
